kabupy/__init__.py
kabupy/exceptions.py
kabupy/base/__init__.py
kabupy/base/decorators.py
kabupy/base/webpage.py
kabupy/base/website.py
kabupy/constants/__init__.py
kabupy/constatns/__init__.py
kabupy/errors/__init__.py
kabupy/jpx/__init__.py
kabupy/jpx/jpx.py
kabupy/kabuyoho/__init__.py
kabupy/kabuyoho/kabuyoho.py
kabupy/kabuyoho/kabuyoho_webpage.py
kabupy/kabuyoho/report_dps.py
kabupy/kabuyoho/report_news.py
kabupy/kabuyoho/report_target.py
kabupy/kabuyoho/report_top.py
kabupy/kabuyoho/report_trend_signal.py
kabupy/util/__init__.py
kabupy-0.0.7.dist-info/WHEEL
kabupy-0.0.7.dist-info/METADATA
kabupy-0.0.7.dist-info/RECORD
