Metadata-Version: 2.1
Name: kabupy
Version: 0.0.7
Summary: A Python package for scraping Japanese stock information from various websites.
Author-email: ReiRev <reirev2913@gmail.com>
Requires-Python: >=3.8.1
Classifier: Development Status :: 3 - Alpha
Classifier: Intended Audience :: Developers
Classifier: License :: OSI Approved :: MIT License
Classifier: Programming Language :: Python :: 3 :: Only
Classifier: Programming Language :: Python :: 3.8
Classifier: Programming Language :: Python :: 3.9
Classifier: Programming Language :: Python :: 3.10
Classifier: Programming Language :: Python :: 3.11
Requires-Dist: requests
Requires-Dist: beautifulsoup4
Requires-Dist: money
Requires-Dist: pandas
Requires-Dist: xlrd
Requires-Dist: sphinx ; extra == "doc"
Requires-Dist: pydata-sphinx-theme ; extra == "doc"
Requires-Dist: sphinx_fontawesome ; extra == "doc"
Requires-Dist: myst-parser ; extra == "doc"
Requires-Dist: sphinx-sitemap ; extra == "doc"
Requires-Dist: bandit[toml]==1.7.5 ; extra == "test"
Requires-Dist: black==23.3.0 ; extra == "test"
Requires-Dist: check-manifest==0.49 ; extra == "test"
Requires-Dist: flake8-bugbear==23.5.9 ; extra == "test"
Requires-Dist: flake8-docstrings ; extra == "test"
Requires-Dist: flake8-formatter_junit_xml ; extra == "test"
Requires-Dist: flake8 ; extra == "test"
Requires-Dist: flake8-pyproject ; extra == "test"
Requires-Dist: autoflake ; extra == "test"
Requires-Dist: pre-commit==3.3.1 ; extra == "test"
Requires-Dist: pylint==2.17.4 ; extra == "test"
Requires-Dist: pylint_junit ; extra == "test"
Requires-Dist: pyright ; extra == "test"
Requires-Dist: pytest-cov==4.0.0 ; extra == "test"
Requires-Dist: pytest-mock<3.10.1 ; extra == "test"
Requires-Dist: pytest-runner ; extra == "test"
Requires-Dist: pytest==7.3.1 ; extra == "test"
Requires-Dist: pytest-github-actions-annotate-failures ; extra == "test"
Requires-Dist: shellcheck-py==0.9.0.2 ; extra == "test"
Requires-Dist: requests_mock ; extra == "test"
Project-URL: Documentation, https://github.com/ReiRev/kabupy/tree/main#readme
Project-URL: Source, https://github.com/ReiRev/kabupy
Project-URL: Tracker, https://github.com/ReiRev/kabupy/issues
Provides-Extra: doc
Provides-Extra: test
